llmtools/HyDE.py
llmtools/__init__.py
llmtools/_modidx.py
llmtools/core.py
llmtools-0.0.2.dist-info/LICENSE
llmtools-0.0.2.dist-info/METADATA
llmtools-0.0.2.dist-info/WHEEL
llmtools-0.0.2.dist-info/entry_points.txt
llmtools-0.0.2.dist-info/top_level.txt
llmtools-0.0.2.dist-info/RECORD
