Metadata-Version: 2.1
Name: llmtools
Version: 0.0.2
Summary: A package with useful functions for working with Large Language Models
Home-page: https://github.com/franfram/llmtools
Author: franfram
Author-email: francis.felici@gmail.com
License: Apache Software License 2.0
Keywords: nbdev jupyter notebook python
Classifier: Development Status :: 4 - Beta
Classifier: Intended Audience :: Developers
Classifier: Natural Language :: English
Classifier: Programming Language :: Python :: 3.7
Classifier: Programming Language :: Python :: 3.8
Classifier: Programming Language :: Python :: 3.9
Classifier: Programming Language :: Python :: 3.10
Classifier: License :: OSI Approved :: Apache Software License
Requires-Python: >=3.7
License-File: LICENSE
Requires-Dist: llama-index
Requires-Dist: langchain
Requires-Dist: transformers
Requires-Dist: torch
Requires-Dist: arxiv
Requires-Dist: accelerate
Requires-Dist: sentence-transformers
Provides-Extra: dev
